administration/__init__.py
administration/admin.py
administration/apps.py
administration/filters.py
administration/utils.py
administration/static/administration/css/label.css
administration/templates/administration/dropdown_filter.html
administration/templates/daterange_filter/filter.html
django_administration-0.2.2.dist-info/DESCRIPTION.rst
django_administration-0.2.2.dist-info/METADATA
django_administration-0.2.2.dist-info/RECORD
django_administration-0.2.2.dist-info/WHEEL
django_administration-0.2.2.dist-info/metadata.json
django_administration-0.2.2.dist-info/top_level.txt
